ayaka_timezone.py
nonebot_plugin_ayaka_timezone-0.4.1.dist-info/LICENSE
nonebot_plugin_ayaka_timezone-0.4.1.dist-info/METADATA
nonebot_plugin_ayaka_timezone-0.4.1.dist-info/WHEEL
nonebot_plugin_ayaka_timezone-0.4.1.dist-info/RECORD
