Metadata-Version: 2.1
Name: nonebot-plugin-ayaka-timezone
Version: 0.4.1
Summary: 时区助手
Home-page: https://github.com/bridgeL/nonebot-plugin-ayaka-timezone
License: MIT
Author: Su
Author-email: wxlxy316@163.com
Classifier: License :: OSI Approved :: MIT License
Classifier: Programming Language :: Python :: 2
Classifier: Programming Language :: Python :: 2.7
Classifier: Programming Language :: Python :: 3
Classifier: Programming Language :: Python :: 3.4
Classifier: Programming Language :: Python :: 3.5
Classifier: Programming Language :: Python :: 3.6
Classifier: Programming Language :: Python :: 3.7
Classifier: Programming Language :: Python :: 3.8
Classifier: Programming Language :: Python :: 3.9
Classifier: Programming Language :: Python :: 3.10
Classifier: Programming Language :: Python :: 3.11
Requires-Dist: ayaka (>=0.0.2.0,<0.0.4.0)
Project-URL: Repository, https://github.com/bridgeL/nonebot-plugin-ayaka-timezone
